{
  "version": "5",
  "dialect": "mysql",
  "id": "64afa02e-e0f6-40d6-a320-2c201db4c402",
  "prevId": "f854230b-0303-4dd3-8edc-83701d604d28",
  "tables": {
    "associados_beneficiarios": {
      "name": "associados_beneficiarios",
      "columns": {
        "id": {
          "name": "id",
          "type": "int",
          "primaryKey": false,
          "notNull": true,
          "autoincrement": true
        },
        "nomeCompleto": {
          "name": "nomeCompleto",
          "type": "varchar(255)",
          "primaryKey": false,
          "notNull": true,
          "autoincrement": false
        },
        "sexo": {
          "name": "sexo",
          "type": "enum('Masculino','Feminino')",
          "primaryKey": false,
          "notNull": true,
          "autoincrement": false
        },
        "naturalidade": {
          "name": "naturalidade",
          "type": "varchar(255)",
          "primaryKey": false,
          "notNull": false,
          "autoincrement": false
        },
        "naturalidadeUf": {
          "name": "naturalidadeUf",
          "type": "varchar(2)",
          "primaryKey": false,
          "notNull": false,
          "autoincrement": false
        },
        "dataNascimento": {
          "name": "dataNascimento",
          "type": "date",
          "primaryKey": false,
          "notNull": true,
          "autoincrement": false
        },
        "escolaridade": {
          "name": "escolaridade",
          "type": "varchar(100)",
          "primaryKey": false,
          "notNull": false,
          "autoincrement": false
        },
        "corRaca": {
          "name": "corRaca",
          "type": "varchar(100)",
          "primaryKey": false,
          "notNull": false,
          "autoincrement": false
        },
        "endereco": {
          "name": "endereco",
          "type": "varchar(255)",
          "primaryKey": false,
          "notNull": false,
          "autoincrement": false
        },
        "enderecoNumero": {
          "name": "enderecoNumero",
          "type": "varchar(20)",
          "primaryKey": false,
          "notNull": false,
          "autoincrement": false
        },
        "enderecoComplemento": {
          "name": "enderecoComplemento",
          "type": "varchar(100)",
          "primaryKey": false,
          "notNull": false,
          "autoincrement": false
        },
        "bairro": {
          "name": "bairro",
          "type": "varchar(100)",
          "primaryKey": false,
          "notNull": false,
          "autoincrement": false
        },
        "cidade": {
          "name": "cidade",
          "type": "varchar(100)",
          "primaryKey": false,
          "notNull": false,
          "autoincrement": false
        },
        "uf": {
          "name": "uf",
          "type": "varchar(2)",
          "primaryKey": false,
          "notNull": false,
          "autoincrement": false
        },
        "cep": {
          "name": "cep",
          "type": "varchar(10)",
          "primaryKey": false,
          "notNull": false,
          "autoincrement": false
        },
        "telResidencial": {
          "name": "telResidencial",
          "type": "varchar(20)",
          "primaryKey": false,
          "notNull": false,
          "autoincrement": false
        },
        "telComercial": {
          "name": "telComercial",
          "type": "varchar(20)",
          "primaryKey": false,
          "notNull": false,
          "autoincrement": false
        },
        "telCelular": {
          "name": "telCelular",
          "type": "varchar(20)",
          "primaryKey": false,
          "notNull": false,
          "autoincrement": false
        },
        "email": {
          "name": "email",
          "type": "varchar(320)",
          "primaryKey": false,
          "notNull": false,
          "autoincrement": false
        },
        "profissao": {
          "name": "profissao",
          "type": "varchar(100)",
          "primaryKey": false,
          "notNull": false,
          "autoincrement": false
        },
        "localTrabalho": {
          "name": "localTrabalho",
          "type": "varchar(255)",
          "primaryKey": false,
          "notNull": false,
          "autoincrement": false
        },
        "rg": {
          "name": "rg",
          "type": "varchar(20)",
          "primaryKey": false,
          "notNull": false,
          "autoincrement": false
        },
        "rgOrgaoExpedidor": {
          "name": "rgOrgaoExpedidor",
          "type": "varchar(50)",
          "primaryKey": false,
          "notNull": false,
          "autoincrement": false
        },
        "cpf": {
          "name": "cpf",
          "type": "varchar(14)",
          "primaryKey": false,
          "notNull": false,
          "autoincrement": false
        },
        "clubeServico": {
          "name": "clubeServico",
          "type": "varchar(255)",
          "primaryKey": false,
          "notNull": false,
          "autoincrement": false
        },
        "religiao": {
          "name": "religiao",
          "type": "varchar(100)",
          "primaryKey": false,
          "notNull": false,
          "autoincrement": false
        },
        "createdAt": {
          "name": "createdAt",
          "type": "timestamp",
          "primaryKey": false,
          "notNull": true,
          "autoincrement": false,
          "default": "(now())"
        },
        "updatedAt": {
          "name": "updatedAt",
          "type": "timestamp",
          "primaryKey": false,
          "notNull": true,
          "autoincrement": false,
          "onUpdate": true,
          "default": "(now())"
        }
      },
      "indexes": {},
      "foreignKeys": {},
      "compositePrimaryKeys": {
        "associados_beneficiarios_id": {
          "name": "associados_beneficiarios_id",
          "columns": [
            "id"
          ]
        }
      },
      "uniqueConstraints": {},
      "checkConstraint": {}
    },
    "fichas_medicas": {
      "name": "fichas_medicas",
      "columns": {
        "id": {
          "name": "id",
          "type": "int",
          "primaryKey": false,
          "notNull": true,
          "autoincrement": true
        },
        "associadoBeneficiarioId": {
          "name": "associadoBeneficiarioId",
          "type": "int",
          "primaryKey": false,
          "notNull": true,
          "autoincrement": false
        },
        "altura": {
          "name": "altura",
          "type": "int",
          "primaryKey": false,
          "notNull": false,
          "autoincrement": false
        },
        "peso": {
          "name": "peso",
          "type": "int",
          "primaryKey": false,
          "notNull": false,
          "autoincrement": false
        },
        "tipoSanguineo": {
          "name": "tipoSanguineo",
          "type": "enum('A','B','AB','O')",
          "primaryKey": false,
          "notNull": false,
          "autoincrement": false
        },
        "fatorRh": {
          "name": "fatorRh",
          "type": "enum('Positivo','Negativo')",
          "primaryKey": false,
          "notNull": false,
          "autoincrement": false
        },
        "usaOculos": {
          "name": "usaOculos",
          "type": "boolean",
          "primaryKey": false,
          "notNull": false,
          "autoincrement": false,
          "default": false
        },
        "usaLentesContato": {
          "name": "usaLentesContato",
          "type": "boolean",
          "primaryKey": false,
          "notNull": false,
          "autoincrement": false,
          "default": false
        },
        "usaAparelhosDentarios": {
          "name": "usaAparelhosDentarios",
          "type": "boolean",
          "primaryKey": false,
          "notNull": false,
          "autoincrement": false,
          "default": false
        },
        "usaSondas": {
          "name": "usaSondas",
          "type": "boolean",
          "primaryKey": false,
          "notNull": false,
          "autoincrement": false,
          "default": false
        },
        "usaMarcapasso": {
          "name": "usaMarcapasso",
          "type": "boolean",
          "primaryKey": false,
          "notNull": false,
          "autoincrement": false,
          "default": false
        },
        "usaAparelhosAudicao": {
          "name": "usaAparelhosAudicao",
          "type": "boolean",
          "primaryKey": false,
          "notNull": false,
          "autoincrement": false,
          "default": false
        },
        "usaBombaInsulina": {
          "name": "usaBombaInsulina",
          "type": "boolean",
          "primaryKey": false,
          "notNull": false,
          "autoincrement": false,
          "default": false
        },
        "outrosEquipamentos": {
          "name": "outrosEquipamentos",
          "type": "text",
          "primaryKey": false,
          "notNull": false,
          "autoincrement": false
        },
        "temAsmaBronquite": {
          "name": "temAsmaBronquite",
          "type": "boolean",
          "primaryKey": false,
          "notNull": false,
          "autoincrement": false,
          "default": false
        },
        "temRiniteSinusite": {
          "name": "temRiniteSinusite",
          "type": "boolean",
          "primaryKey": false,
          "notNull": false,
          "autoincrement": false,
          "default": false
        },
        "temHipertensao": {
          "name": "temHipertensao",
          "type": "boolean",
          "primaryKey": false,
          "notNull": false,
          "autoincrement": false,
          "default": false
        },
        "temDiabetes": {
          "name": "temDiabetes",
          "type": "boolean",
          "primaryKey": false,
          "notNull": false,
          "autoincrement": false,
          "default": false
        },
        "temConvulsoesEpilepsia": {
          "name": "temConvulsoesEpilepsia",
          "type": "boolean",
          "primaryKey": false,
          "notNull": false,
          "autoincrement": false,
          "default": false
        },
        "temProblemasDermatologicos": {
          "name": "temProblemasDermatologicos",
          "type": "boolean",
          "primaryKey": false,
          "notNull": false,
          "autoincrement": false,
          "default": false
        },
        "temProblemasCardiacos": {
          "name": "temProblemasCardiacos",
          "type": "boolean",
          "primaryKey": false,
          "notNull": false,
          "autoincrement": false,
          "default": false
        },
        "temProblemasRenais": {
          "name": "temProblemasRenais",
          "type": "boolean",
          "primaryKey": false,
          "notNull": false,
          "autoincrement": false,
          "default": false
        },
        "temProblemasReumatologicos": {
          "name": "temProblemasReumatologicos",
          "type": "boolean",
          "primaryKey": false,
          "notNull": false,
          "autoincrement": false,
          "default": false
        },
        "temProblemasHematologicos": {
          "name": "temProblemasHematologicos",
          "type": "boolean",
          "primaryKey": false,
          "notNull": false,
          "autoincrement": false,
          "default": false
        },
        "outrosProblemasSaude": {
          "name": "outrosProblemasSaude",
          "type": "text",
          "primaryKey": false,
          "notNull": false,
          "autoincrement": false
        },
        "medicamentosContinuo": {
          "name": "medicamentosContinuo",
          "type": "boolean",
          "primaryKey": false,
          "notNull": false,
          "autoincrement": false,
          "default": false
        },
        "listaMedicamentos": {
          "name": "listaMedicamentos",
          "type": "text",
          "primaryKey": false,
          "notNull": false,
          "autoincrement": false
        },
        "autonomiaMedicacao": {
          "name": "autonomiaMedicacao",
          "type": "boolean",
          "primaryKey": false,
          "notNull": false,
          "autoincrement": false,
          "default": false
        },
        "permiteAdminMedicacaoGrupo": {
          "name": "permiteAdminMedicacaoGrupo",
          "type": "boolean",
          "primaryKey": false,
          "notNull": false,
          "autoincrement": false,
          "default": false
        },
        "aguardarPaisEmergencia": {
          "name": "aguardarPaisEmergencia",
          "type": "boolean",
          "primaryKey": false,
          "notNull": false,
          "autoincrement": false,
          "default": false
        },
        "aceitaDecisoesMedicas": {
          "name": "aceitaDecisoesMedicas",
          "type": "boolean",
          "primaryKey": false,
          "notNull": false,
          "autoincrement": false,
          "default": false
        },
        "avisarEmergencia": {
          "name": "avisarEmergencia",
          "type": "varchar(100)",
          "primaryKey": false,
          "notNull": false,
          "autoincrement": false
        },
        "planoSaudeTipo": {
          "name": "planoSaudeTipo",
          "type": "varchar(50)",
          "primaryKey": false,
          "notNull": false,
          "autoincrement": false
        },
        "planoSaudeNome": {
          "name": "planoSaudeNome",
          "type": "varchar(255)",
          "primaryKey": false,
          "notNull": false,
          "autoincrement": false
        },
        "planoSaudeCarteirinha": {
          "name": "planoSaudeCarteirinha",
          "type": "varchar(100)",
          "primaryKey": false,
          "notNull": false,
          "autoincrement": false
        },
        "planoSaudeTelefone": {
          "name": "planoSaudeTelefone",
          "type": "varchar(20)",
          "primaryKey": false,
          "notNull": false,
          "autoincrement": false
        },
        "medicoPreferenciaNome": {
          "name": "medicoPreferenciaNome",
          "type": "varchar(255)",
          "primaryKey": false,
          "notNull": false,
          "autoincrement": false
        },
        "medicoPreferenciaTelefone": {
          "name": "medicoPreferenciaTelefone",
          "type": "varchar(20)",
          "primaryKey": false,
          "notNull": false,
          "autoincrement": false
        },
        "temAlergias": {
          "name": "temAlergias",
          "type": "boolean",
          "primaryKey": false,
          "notNull": false,
          "autoincrement": false,
          "default": false
        },
        "alergiaPicadaInseto": {
          "name": "alergiaPicadaInseto",
          "type": "text",
          "primaryKey": false,
          "notNull": false,
          "autoincrement": false
        },
        "alergiaMedicamentos": {
          "name": "alergiaMedicamentos",
          "type": "text",
          "primaryKey": false,
          "notNull": false,
          "autoincrement": false
        },
        "alergiaPlantas": {
          "name": "alergiaPlantas",
          "type": "text",
          "primaryKey": false,
          "notNull": false,
          "autoincrement": false
        },
        "alergiaAlimentos": {
          "name": "alergiaAlimentos",
          "type": "text",
          "primaryKey": false,
          "notNull": false,
          "autoincrement": false
        },
        "alergiaAcaros": {
          "name": "alergiaAcaros",
          "type": "text",
          "primaryKey": false,
          "notNull": false,
          "autoincrement": false
        },
        "alergiaFungos": {
          "name": "alergiaFungos",
          "type": "text",
          "primaryKey": false,
          "notNull": false,
          "autoincrement": false
        },
        "alergiaOutros": {
          "name": "alergiaOutros",
          "type": "text",
          "primaryKey": false,
          "notNull": false,
          "autoincrement": false
        },
        "impedimentoFisico": {
          "name": "impedimentoFisico",
          "type": "boolean",
          "primaryKey": false,
          "notNull": false,
          "autoincrement": false,
          "default": false
        },
        "impedimentoFisicoDesc": {
          "name": "impedimentoFisicoDesc",
          "type": "text",
          "primaryKey": false,
          "notNull": false,
          "autoincrement": false
        },
        "restricoesAlimentos": {
          "name": "restricoesAlimentos",
          "type": "boolean",
          "primaryKey": false,
          "notNull": false,
          "autoincrement": false,
          "default": false
        },
        "restricoesAlimentosDesc": {
          "name": "restricoesAlimentosDesc",
          "type": "text",
          "primaryKey": false,
          "notNull": false,
          "autoincrement": false
        },
        "sabeNadar": {
          "name": "sabeNadar",
          "type": "boolean",
          "primaryKey": false,
          "notNull": false,
          "autoincrement": false,
          "default": false
        },
        "disturbioComportamento": {
          "name": "disturbioComportamento",
          "type": "boolean",
          "primaryKey": false,
          "notNull": false,
          "autoincrement": false,
          "default": false
        },
        "disturbioComportamentoDesc": {
          "name": "disturbioComportamentoDesc",
          "type": "text",
          "primaryKey": false,
          "notNull": false,
          "autoincrement": false
        },
        "medicacaoTranstorno": {
          "name": "medicacaoTranstorno",
          "type": "boolean",
          "primaryKey": false,
          "notNull": false,
          "autoincrement": false,
          "default": false
        },
        "medicacaoTranstornoDesc": {
          "name": "medicacaoTranstornoDesc",
          "type": "text",
          "primaryKey": false,
          "notNull": false,
          "autoincrement": false
        },
        "acompanhamentoPsicologo": {
          "name": "acompanhamentoPsicologo",
          "type": "boolean",
          "primaryKey": false,
          "notNull": false,
          "autoincrement": false,
          "default": false
        },
        "acompanhamentoPsicologoDesc": {
          "name": "acompanhamentoPsicologoDesc",
          "type": "text",
          "primaryKey": false,
          "notNull": false,
          "autoincrement": false
        },
        "acompanhamentoMedico": {
          "name": "acompanhamentoMedico",
          "type": "boolean",
          "primaryKey": false,
          "notNull": false,
          "autoincrement": false,
          "default": false
        },
        "acompanhamentoMedicoDesc": {
          "name": "acompanhamentoMedicoDesc",
          "type": "text",
          "primaryKey": false,
          "notNull": false,
          "autoincrement": false
        },
        "acompanhamentoOutroProf": {
          "name": "acompanhamentoOutroProf",
          "type": "boolean",
          "primaryKey": false,
          "notNull": false,
          "autoincrement": false,
          "default": false
        },
        "acompanhamentoOutroProfDesc": {
          "name": "acompanhamentoOutroProfDesc",
          "type": "text",
          "primaryKey": false,
          "notNull": false,
          "autoincrement": false
        },
        "temDeficiencias": {
          "name": "temDeficiencias",
          "type": "boolean",
          "primaryKey": false,
          "notNull": false,
          "autoincrement": false,
          "default": false
        },
        "deficienciaFisica": {
          "name": "deficienciaFisica",
          "type": "text",
          "primaryKey": false,
          "notNull": false,
          "autoincrement": false
        },
        "deficienciaVisual": {
          "name": "deficienciaVisual",
          "type": "text",
          "primaryKey": false,
          "notNull": false,
          "autoincrement": false
        },
        "deficienciaAuditiva": {
          "name": "deficienciaAuditiva",
          "type": "text",
          "primaryKey": false,
          "notNull": false,
          "autoincrement": false
        },
        "deficienciaIntelectual": {
          "name": "deficienciaIntelectual",
          "type": "text",
          "primaryKey": false,
          "notNull": false,
          "autoincrement": false
        },
        "criseExplosaoSiMesmo": {
          "name": "criseExplosaoSiMesmo",
          "type": "boolean",
          "primaryKey": false,
          "notNull": false,
          "autoincrement": false,
          "default": false
        },
        "criseExplosaoSiMesmoDesc": {
          "name": "criseExplosaoSiMesmoDesc",
          "type": "text",
          "primaryKey": false,
          "notNull": false,
          "autoincrement": false
        },
        "criseExplosaoOutros": {
          "name": "criseExplosaoOutros",
          "type": "boolean",
          "primaryKey": false,
          "notNull": false,
          "autoincrement": false,
          "default": false
        },
        "criseExplosaoOutrosDesc": {
          "name": "criseExplosaoOutrosDesc",
          "type": "text",
          "primaryKey": false,
          "notNull": false,
          "autoincrement": false
        },
        "agitacaoPsicomotora": {
          "name": "agitacaoPsicomotora",
          "type": "boolean",
          "primaryKey": false,
          "notNull": false,
          "autoincrement": false,
          "default": false
        },
        "agitacaoPsicomotoraDesc": {
          "name": "agitacaoPsicomotoraDesc",
          "type": "text",
          "primaryKey": false,
          "notNull": false,
          "autoincrement": false
        },
        "dificuldadeInstrucoesVerbais": {
          "name": "dificuldadeInstrucoesVerbais",
          "type": "boolean",
          "primaryKey": false,
          "notNull": false,
          "autoincrement": false,
          "default": false
        },
        "dificuldadeInstrucoesVerbaisDesc": {
          "name": "dificuldadeInstrucoesVerbaisDesc",
          "type": "text",
          "primaryKey": false,
          "notNull": false,
          "autoincrement": false
        },
        "tendenciaFugas": {
          "name": "tendenciaFugas",
          "type": "boolean",
          "primaryKey": false,
          "notNull": false,
          "autoincrement": false,
          "default": false
        },
        "tendenciaFugasDesc": {
          "name": "tendenciaFugasDesc",
          "type": "text",
          "primaryKey": false,
          "notNull": false,
          "autoincrement": false
        },
        "comportamentoAutodestrutivo": {
          "name": "comportamentoAutodestrutivo",
          "type": "boolean",
          "primaryKey": false,
          "notNull": false,
          "autoincrement": false,
          "default": false
        },
        "comportamentoAutodestrutivoDesc": {
          "name": "comportamentoAutodestrutivoDesc",
          "type": "text",
          "primaryKey": false,
          "notNull": false,
          "autoincrement": false
        },
        "crisesAnsiedadePanico": {
          "name": "crisesAnsiedadePanico",
          "type": "boolean",
          "primaryKey": false,
          "notNull": false,
          "autoincrement": false,
          "default": false
        },
        "crisesAnsiedadePanicoDesc": {
          "name": "crisesAnsiedadePanicoDesc",
          "type": "text",
          "primaryKey": false,
          "notNull": false,
          "autoincrement": false
        },
        "dificuldadeComunicacao": {
          "name": "dificuldadeComunicacao",
          "type": "boolean",
          "primaryKey": false,
          "notNull": false,
          "autoincrement": false,
          "default": false
        },
        "dificuldadeComunicacaoDesc": {
          "name": "dificuldadeComunicacaoDesc",
          "type": "text",
          "primaryKey": false,
          "notNull": false,
          "autoincrement": false
        },
        "dificuldadesAlimentares": {
          "name": "dificuldadesAlimentares",
          "type": "boolean",
          "primaryKey": false,
          "notNull": false,
          "autoincrement": false,
          "default": false
        },
        "dificuldadesAlimentaresDesc": {
          "name": "dificuldadesAlimentaresDesc",
          "type": "text",
          "primaryKey": false,
          "notNull": false,
          "autoincrement": false
        },
        "dificuldadesSono": {
          "name": "dificuldadesSono",
          "type": "boolean",
          "primaryKey": false,
          "notNull": false,
          "autoincrement": false,
          "default": false
        },
        "dificuldadesSonoDesc": {
          "name": "dificuldadesSonoDesc",
          "type": "text",
          "primaryKey": false,
          "notNull": false,
          "autoincrement": false
        },
        "dataUltimaAtualizacao": {
          "name": "dataUltimaAtualizacao",
          "type": "date",
          "primaryKey": false,
          "notNull": false,
          "autoincrement": false
        },
        "createdAt": {
          "name": "createdAt",
          "type": "timestamp",
          "primaryKey": false,
          "notNull": true,
          "autoincrement": false,
          "default": "(now())"
        },
        "updatedAt": {
          "name": "updatedAt",
          "type": "timestamp",
          "primaryKey": false,
          "notNull": true,
          "autoincrement": false,
          "onUpdate": true,
          "default": "(now())"
        }
      },
      "indexes": {},
      "foreignKeys": {},
      "compositePrimaryKeys": {
        "fichas_medicas_id": {
          "name": "fichas_medicas_id",
          "columns": [
            "id"
          ]
        }
      },
      "uniqueConstraints": {
        "fichas_medicas_associadoBeneficiarioId_unique": {
          "name": "fichas_medicas_associadoBeneficiarioId_unique",
          "columns": [
            "associadoBeneficiarioId"
          ]
        }
      },
      "checkConstraint": {}
    },
    "responsaveis_legais": {
      "name": "responsaveis_legais",
      "columns": {
        "id": {
          "name": "id",
          "type": "int",
          "primaryKey": false,
          "notNull": true,
          "autoincrement": true
        },
        "associadoBeneficiarioId": {
          "name": "associadoBeneficiarioId",
          "type": "int",
          "primaryKey": false,
          "notNull": true,
          "autoincrement": false
        },
        "nomeCompleto": {
          "name": "nomeCompleto",
          "type": "varchar(255)",
          "primaryKey": false,
          "notNull": true,
          "autoincrement": false
        },
        "parentesco": {
          "name": "parentesco",
          "type": "enum('Pai','Mãe','Tutor')",
          "primaryKey": false,
          "notNull": true,
          "autoincrement": false
        },
        "sexo": {
          "name": "sexo",
          "type": "enum('Masculino','Feminino')",
          "primaryKey": false,
          "notNull": true,
          "autoincrement": false
        },
        "naturalDe": {
          "name": "naturalDe",
          "type": "varchar(255)",
          "primaryKey": false,
          "notNull": false,
          "autoincrement": false
        },
        "naturalUf": {
          "name": "naturalUf",
          "type": "varchar(2)",
          "primaryKey": false,
          "notNull": false,
          "autoincrement": false
        },
        "dataNascimento": {
          "name": "dataNascimento",
          "type": "date",
          "primaryKey": false,
          "notNull": false,
          "autoincrement": false
        },
        "escolaridade": {
          "name": "escolaridade",
          "type": "varchar(100)",
          "primaryKey": false,
          "notNull": false,
          "autoincrement": false
        },
        "corRaca": {
          "name": "corRaca",
          "type": "varchar(100)",
          "primaryKey": false,
          "notNull": false,
          "autoincrement": false
        },
        "endereco": {
          "name": "endereco",
          "type": "varchar(255)",
          "primaryKey": false,
          "notNull": false,
          "autoincrement": false
        },
        "enderecoNumero": {
          "name": "enderecoNumero",
          "type": "varchar(20)",
          "primaryKey": false,
          "notNull": false,
          "autoincrement": false
        },
        "enderecoComplemento": {
          "name": "enderecoComplemento",
          "type": "varchar(100)",
          "primaryKey": false,
          "notNull": false,
          "autoincrement": false
        },
        "bairro": {
          "name": "bairro",
          "type": "varchar(100)",
          "primaryKey": false,
          "notNull": false,
          "autoincrement": false
        },
        "cidade": {
          "name": "cidade",
          "type": "varchar(100)",
          "primaryKey": false,
          "notNull": false,
          "autoincrement": false
        },
        "uf": {
          "name": "uf",
          "type": "varchar(2)",
          "primaryKey": false,
          "notNull": false,
          "autoincrement": false
        },
        "cep": {
          "name": "cep",
          "type": "varchar(10)",
          "primaryKey": false,
          "notNull": false,
          "autoincrement": false
        },
        "telResidencial": {
          "name": "telResidencial",
          "type": "varchar(20)",
          "primaryKey": false,
          "notNull": false,
          "autoincrement": false
        },
        "telComercial": {
          "name": "telComercial",
          "type": "varchar(20)",
          "primaryKey": false,
          "notNull": false,
          "autoincrement": false
        },
        "telCelular": {
          "name": "telCelular",
          "type": "varchar(20)",
          "primaryKey": false,
          "notNull": false,
          "autoincrement": false
        },
        "email": {
          "name": "email",
          "type": "varchar(320)",
          "primaryKey": false,
          "notNull": false,
          "autoincrement": false
        },
        "profissao": {
          "name": "profissao",
          "type": "varchar(100)",
          "primaryKey": false,
          "notNull": false,
          "autoincrement": false
        },
        "localTrabalho": {
          "name": "localTrabalho",
          "type": "varchar(255)",
          "primaryKey": false,
          "notNull": false,
          "autoincrement": false
        },
        "rg": {
          "name": "rg",
          "type": "varchar(20)",
          "primaryKey": false,
          "notNull": false,
          "autoincrement": false
        },
        "rgOrgaoExpedidor": {
          "name": "rgOrgaoExpedidor",
          "type": "varchar(50)",
          "primaryKey": false,
          "notNull": false,
          "autoincrement": false
        },
        "cpf": {
          "name": "cpf",
          "type": "varchar(14)",
          "primaryKey": false,
          "notNull": false,
          "autoincrement": false
        },
        "createdAt": {
          "name": "createdAt",
          "type": "timestamp",
          "primaryKey": false,
          "notNull": true,
          "autoincrement": false,
          "default": "(now())"
        },
        "updatedAt": {
          "name": "updatedAt",
          "type": "timestamp",
          "primaryKey": false,
          "notNull": true,
          "autoincrement": false,
          "onUpdate": true,
          "default": "(now())"
        }
      },
      "indexes": {},
      "foreignKeys": {},
      "compositePrimaryKeys": {
        "responsaveis_legais_id": {
          "name": "responsaveis_legais_id",
          "columns": [
            "id"
          ]
        }
      },
      "uniqueConstraints": {},
      "checkConstraint": {}
    },
    "users": {
      "name": "users",
      "columns": {
        "id": {
          "name": "id",
          "type": "int",
          "primaryKey": false,
          "notNull": true,
          "autoincrement": true
        },
        "openId": {
          "name": "openId",
          "type": "varchar(64)",
          "primaryKey": false,
          "notNull": true,
          "autoincrement": false
        },
        "name": {
          "name": "name",
          "type": "text",
          "primaryKey": false,
          "notNull": false,
          "autoincrement": false
        },
        "email": {
          "name": "email",
          "type": "varchar(320)",
          "primaryKey": false,
          "notNull": false,
          "autoincrement": false
        },
        "loginMethod": {
          "name": "loginMethod",
          "type": "varchar(64)",
          "primaryKey": false,
          "notNull": false,
          "autoincrement": false
        },
        "role": {
          "name": "role",
          "type": "enum('user','admin')",
          "primaryKey": false,
          "notNull": true,
          "autoincrement": false,
          "default": "'user'"
        },
        "createdAt": {
          "name": "createdAt",
          "type": "timestamp",
          "primaryKey": false,
          "notNull": true,
          "autoincrement": false,
          "default": "(now())"
        },
        "updatedAt": {
          "name": "updatedAt",
          "type": "timestamp",
          "primaryKey": false,
          "notNull": true,
          "autoincrement": false,
          "onUpdate": true,
          "default": "(now())"
        },
        "lastSignedIn": {
          "name": "lastSignedIn",
          "type": "timestamp",
          "primaryKey": false,
          "notNull": true,
          "autoincrement": false,
          "default": "(now())"
        }
      },
      "indexes": {},
      "foreignKeys": {},
      "compositePrimaryKeys": {
        "users_id": {
          "name": "users_id",
          "columns": [
            "id"
          ]
        }
      },
      "uniqueConstraints": {
        "users_openId_unique": {
          "name": "users_openId_unique",
          "columns": [
            "openId"
          ]
        }
      },
      "checkConstraint": {}
    }
  },
  "views": {},
  "_meta": {
    "schemas": {},
    "tables": {},
    "columns": {}
  },
  "internal": {
    "tables": {},
    "indexes": {}
  }
}